<?xml version="1.0" encoding="UTF-8"?>

<form>
   <table_supported>
      <name>avg_unit_by_parent</name>
      <key>ID</key>
      <key1>UNIT_ID</key1>
         
   </table_supported>  
   
   <form_element>
     <name>unitId</name>
     <table>avg_unit_by_parent</table>
     <column>ID</column>
     <class>com.silkworm.persistence.relational.StringValue</class>
     <jclass>java.lang.String</jclass>
     <matchon>=</matchon>
   </form_element>
   
   
   <form_element>
     <name>unitName</name>
     <table>avg_unit_by_parent</table>
     <column>UNIT_NAME</column>
     <class>com.silkworm.persistence.relational.StringValue</class>
     <jclass>java.lang.String</jclass>
     <matchon>=</matchon>
   </form_element>
   
   
    <form_element>
     <name>current_Reading</name>
     <table>avg_unit_by_parent</table>
     <column>CURRENT_READING</column>
     <class>com.silkworm.persistence.relational.IntValue</class>
     <jclass>java.lang.Integer</jclass>
     <matchon>=</matchon>
   </form_element>
   
   <form_element>
     <name>acual_Reading</name>
     <table>avg_unit_by_parent</table>
     <column>ACUAL_READING</column>
     <class>com.silkworm.persistence.relational.IntValue</class>
     <jclass>java.lang.Integer</jclass>
     <matchon>=</matchon>
   </form_element>
   
   <form_element>
     <name>entry_Time</name>
     <table>avg_unit_by_parent</table>
     <column>ENTRY_TIME</column>
     <class>com.silkworm.persistence.relational.TimeStampValue</class>
     <jclass>java.sql.Timestamp</jclass>
     <matchon>=</matchon>
   </form_element>
   
   <form_element>
     <name>previousTime</name>
     <table>avg_unit_by_parent</table>
     <column>PREVIOUS_TIME</column>
     <class>com.silkworm.persistence.relational.TimeStampValue</class>
     <jclass>java.sql.Timestamp</jclass>
     <matchon>=</matchon>
   </form_element>
   
   
    <form_element>
     <name>description</name>
     <table>avg_unit_by_parent</table>
     <column>DESCRIPTION</column>
     <class>com.silkworm.persistence.relational.StringValue</class>
     <jclass>java.lang.String</jclass>
     <matchon>=</matchon>
   </form_element>

   <form_element>
        <name>parentId</name>
        <table>avg_unit_by_parent</table>
        <column>PARENT_ID</column>
        <class>com.silkworm.persistence.relational.StringValue</class>
        <jclass>java.lang.String</jclass>
        <matchon>=</matchon>
    </form_element>
     
</form>