<?xml version="1.0" encoding="UTF-8"?>

<form>
    <table_supported>
        <name>ISSUE_DOCUMENT</name>
        <key>DOCUMENT_ID</key>
        <key2>DOCUMENT_TITLE</key2>
        <key3>ISSUE_ID</key3>
        <key4>CONFIG_ITEM_TYPE</key4>
        <key5>BUSINESS_OBJ_ID</key5>
    </table_supported>  
    
    <form_element>
        <name>documentID</name>
        <table>ISSUE_DOCUMENT</table>
        <column>DOCUMENT_ID</column>
        <class>com.silkworm.persistence.relational.StringValue</class>
        <jclass>java.lang.String</jclass>
        <matchon>=</matchon>
    </form_element>
    <form_element>
        <name>documentTitle</name>
        <table>ISSUE_DOCUMENT</table>
        <column>DOCUMENT_TITLE</column>
        <class>com.silkworm.persistence.relational.StringValue</class>
        <jclass>java.lang.String</jclass>
        <matchon>=</matchon>
    </form_element>
    <form_element>
        <name>businessObjectId</name>
        <table>ISSUE_DOCUMENT</table>
        <column>BUSINESS_OBJ_ID</column>
        <class>com.silkworm.persistence.relational.StringValue</class>
        <jclass>java.lang.String</jclass>
        <matchon>=</matchon>
    </form_element>
    <form_element>
        <name>objectType</name>
        <table>ISSUE_DOCUMENT</table>
        <column>OBJECT_TYPE</column>
        <class>com.silkworm.persistence.relational.StringValue</class>
        <jclass>java.lang.String</jclass>
        <matchon>=</matchon>
    </form_element>
    <form_element>
        <name>description</name>
        <table>ISSUE_DOCUMENT</table>
        <column>DESCRIPTION</column>
        <class>com.silkworm.persistence.relational.StringValue</class>
        <jclass>java.lang.String</jclass>
        <matchon>=</matchon>
    </form_element>
    <form_element>
        <name>documentDate</name>
        <table>ISSUE_DOCUMENT</table>
        <column>DOCUMENT_DATE</column>
        <class>com.silkworm.persistence.relational.DateValue</class>
        <jclass>java.util.Date</jclass>
        <matchon>=</matchon>
    </form_element>
    <form_element>
        <name>fromDate</name>
        <table>ISSUE_DOCUMENT</table>
        <column>DOCUMENT_DATE</column>
        <class>com.silkworm.persistence.relational.DateValue</class>
        <jclass>java.sql.Timestamp</jclass>
        <matchon>></matchon>
    </form_element>
    <form_element>
        <name>createdById</name>
        <table>ISSUE_DOCUMENT</table>
        <column>CREATED_BY</column>
        <class>com.silkworm.persistence.relational.StringValue</class>
        <jclass>java.lang.String</jclass>
        <matchon>=</matchon>
    </form_element>
    <form_element>
        <name>createdBy</name>
        <table>ISSUE_DOCUMENT</table>
        <column>CREATED_BY_NAME</column>
        <class>com.silkworm.persistence.relational.StringValue</class>
        <jclass>java.lang.String</jclass>
        <matchon>=</matchon>
    </form_element> 
    <form_element>
        <name>metaType</name>
        <table>ISSUE_DOCUMENT</table>
        <column>DOCUMENT_META_TYPE</column>
        <class>com.silkworm.persistence.relational.StringValue</class>
        <jclass>java.lang.String</jclass>
        <matchon>=</matchon>
    </form_element>
    <form_element>
        <name>documentType</name>
        <table>ISSUE_DOCUMENT</table>
        <column>DOCUMENT_TYPE</column>
        <class>com.silkworm.persistence.relational.StringValue</class>
        <jclass>java.lang.String</jclass>
        <matchon>=</matchon>
    </form_element>
    <form_element>
        <name>configItemType</name>
        <table>ISSUE_DOCUMENT</table>
        <column>CONFIG_ITEM_TYPE</column>
        <class>com.silkworm.persistence.relational.StringValue</class>
        <jclass>java.lang.String</jclass>
        <matchon>=</matchon>
    </form_element>
    <form_element>
        <name>creationTime</name>
        <table>ISSUE_DOCUMENT</table>
        <column>CREATION_TIME</column>
        <class>com.silkworm.persistence.relational.TimeStampValue</class>
        <jclass>java.sql.Timestamp</jclass>
        <matchon>=</matchon>
    </form_element>
    <form_element>
        <name>option1</name>
        <table>ISSUE_DOCUMENT</table>
        <column>OPTION1</column>
        <class>com.silkworm.persistence.relational.StringValue</class>
        <jclass>java.lang.String</jclass>
        <matchon>=</matchon>
    </form_element>
    <form_element>
        <name>option2</name>
        <table>ISSUE_DOCUMENT</table>
        <column>OPTION2</column>
        <class>com.silkworm.persistence.relational.StringValue</class>
        <jclass>java.lang.String</jclass>
        <matchon>=</matchon>
    </form_element>
    <form_element>
        <name>option3</name>
        <table>ISSUE_DOCUMENT</table>
        <column>OPTION3</column>
        <class>com.silkworm.persistence.relational.StringValue</class>
        <jclass>java.lang.String</jclass>
        <matchon>=</matchon>
    </form_element>
</form>
