<?xml version="1.0" encoding="UTF-8"?>

<form>
    <table_supported>
        <name>trade</name>
        <key>ID</key>
        <key1>NAME</key1>
        <key2>CODE</key2>
        <key3>FLAGE</key3>
        <key4>TRADE_TYPE</key4>
        <keyname>NAME</keyname>
    </table_supported>  
   
    <form_element>
        <name>tradeId</name>
        <table>trade</table>
        <column>ID</column>
        <class>com.silkworm.persistence.relational.StringValue</class>
        <jclass>java.lang.String</jclass>
        <matchon>=</matchon>
    </form_element>
   
    <form_element>
        <name>tradeName</name>
        <table>trade</table>
        <column>NAME</column>
        <class>com.silkworm.persistence.relational.StringValue</class>
        <jclass>java.lang.String</jclass>
        <matchon>=</matchon>
    </form_element>
    <form_element>
        <name>enName</name>
        <table>trade</table>
        <column>EN_NAME</column>
        <class>com.silkworm.persistence.relational.StringValue</class>
        <jclass>java.lang.String</jclass>
        <matchon>=</matchon>
    </form_element>
    <form_element>
        <name>flage</name>
        <table>trade</table>
        <column>FLAGE</column>
        <class>com.silkworm.persistence.relational.StringValue</class>
        <jclass>java.lang.String</jclass>
        <matchon>=</matchon>
    </form_element>
    <form_element>
            <name>tradeCode</name>
        <table>trade</table>
        <column>CODE</column>
        <class>com.silkworm.persistence.relational.StringValue</class>
        <jclass>java.lang.String</jclass>
        <matchon>=</matchon>
    </form_element>
       <form_element>
            <name>createdBy</name>
        <table>trade</table>
        <column>CREATED_BY</column>
        <class>com.silkworm.persistence.relational.StringValue</class>
        <jclass>java.lang.String</jclass>
        <matchon>=</matchon>
    </form_element>
        <form_element>
            <name>creationTime</name>
        <table>trade</table>
        <column>CREATION_TIME</column>
        <class>com.silkworm.persistence.relational.StringValue</class>
        <jclass>java.lang.String</jclass>
        <matchon>=</matchon>
    </form_element>
         <form_element>
            <name>tradeType</name>
        <table>trade</table>
        <column>TRADE_TYPE</column>
        <class>com.silkworm.persistence.relational.StringValue</class>
        <jclass>java.lang.String</jclass>
        <matchon>=</matchon>
    </form_element>
        <form_element>
            <name>option1</name>
        <table>trade</table>
        <column>OPTION1</column>
        <class>com.silkworm.persistence.relational.StringValue</class>
        <jclass>java.lang.String</jclass>
        <matchon>=</matchon>
    </form_element>
        <form_element>
            <name>option2</name>
        <table>trade</table>
        <column>OPTION2</column>
        <class>com.silkworm.persistence.relational.StringValue</class>
        <jclass>java.lang.String</jclass>
        <matchon>=</matchon>
    </form_element>
</form>
